packagetext/__init__.py
packagetext-0.0.1.dist-info/License.txt
packagetext-0.0.1.dist-info/METADATA
packagetext-0.0.1.dist-info/WHEEL
packagetext-0.0.1.dist-info/top_level.txt
packagetext-0.0.1.dist-info/RECORD
